mercury/__init__.py
mercury/backend/__init__.py
mercury/backend/active_asyncio.py
mercury/backend/configuration.py
mercury/backend/controller.py
mercury/backend/options.py
mercury/backend/rpc_client.py
mercury/backend/service.py
mercury/backend/queue_service/__init__.py
mercury/backend/queue_service/options.py
mercury/backend/queue_service/service.py
mercury/backend/queue_service/slow_async_implementation.py
mercury/backend/workers/__init__.py
mercury/backend/workers/service.py
mercury/boot/__init__.py
mercury/boot/app.py
mercury/boot/configuration.py
mercury/boot/service.py
mercury/boot/urls.py
mercury/boot/views.py
mercury/common/__init__.py
mercury/common/configuration.py
mercury/common/exceptions.py
mercury/common/log.py
mercury/common/mercury_id.py
mercury/common/mongo.py
mercury/common/transport.py
mercury/common/asyncio/__init__.py
mercury/common/asyncio/dispatcher.py
mercury/common/asyncio/endpoints.py
mercury/common/asyncio/mongo.py
mercury/common/asyncio/transport.py
mercury/common/asyncio/clients/__init__.py
mercury/common/asyncio/clients/async_router_req_client.py
mercury/common/asyncio/clients/inventory.py
mercury/common/clients/__init__.py
mercury/common/clients/inventory.py
mercury/common/clients/router_req_client.py
mercury/common/clients/rpc/__init__.py
mercury/common/clients/rpc/backend.py
mercury/common/clients/rpc/frontend.py
mercury/common/clients/rpc/queue.py
mercury/common/helpers/__init__.py
mercury/common/helpers/cli.py
mercury/common/helpers/size.py
mercury/common/helpers/util.py
mercury/common/inventory_client/__init__.py
mercury/common/models/__init__.py
mercury/common/models/computer.py
mercury/common/task_managers/__init__.py
mercury/common/task_managers/base/__init__.py
mercury/common/task_managers/base/manager.py
mercury/common/task_managers/base/task.py
mercury/common/task_managers/base/worker.py
mercury/common/task_managers/redis/__init__.py
mercury/common/task_managers/redis/task.py
mercury/inventory/__init__.py
mercury_core-0.1.10.dist-info/METADATA
mercury_core-0.1.10.dist-info/WHEEL
mercury_core-0.1.10.dist-info/entry_points.txt
mercury_core-0.1.10.dist-info/top_level.txt
mercury_core-0.1.10.dist-info/RECORD
