Metadata-Version: 2.1
Name: mercury-core
Version: 0.1.10
Summary: Mercury core services and libraries
Home-page: http://www.mercurysoft.io
Author: Jared Rodriguez
Author-email: jared.rodriguez@rackspace.com
License: Apache-2.0
Platform: UNKNOWN
Requires-Dist: PyYAML
Requires-Dist: msgpack-python
Requires-Dist: pymongo
Requires-Dist: pyzmq
Requires-Dist: redis
Requires-Dist: motor
Requires-Dist: python-box
Requires-Dist: requests
Requires-Dist: lxml
Requires-Dist: pystache
Requires-Dist: flask
